LICENSE.txt
MANIFEST.in
README.md
setup.py
origin_routing_machine.egg-info/PKG-INFO
origin_routing_machine.egg-info/SOURCES.txt
origin_routing_machine.egg-info/dependency_links.txt
origin_routing_machine.egg-info/entry_points.txt
origin_routing_machine.egg-info/requires.txt
origin_routing_machine.egg-info/top_level.txt
orm/__init__.py
orm/__main__.py
orm/constants.py
orm/parser.py
orm/render.py
orm/renderhaproxy.py
orm/rendervarnish.py
orm/runtests.py
orm/validator.py
orm/schemas/common-1.json
orm/schemas/globals-1.json
orm/schemas/rules-1.json
orm/templates/haproxy.cfg.j2
orm/templates/varnish.vcl.j2