Metadata-Version: 1.0
Name: origin-routing-machine
Version: 1.2.0
Summary: Origin Routing Machine. Generating config for HTTP routing software.
Home-page: https://github.com/SVT/orm
Author: Webcore Infra
Author-email: webcore-infra@svt.se
License: MIT License
Platform: UNKNOWN
